<?xml version="1.0"?>
<!DOCTYPE hibernate-mapping PUBLIC
   "-//Hibernate/Hibernate Mapping DTD 3.0//EN"
   "http://hibernate.sourceforge.net/hibernate-mapping-3.0.dtd">

<hibernate-mapping>
	<class  lazy="false"  name="com.bestway.bcus.cas.entity.BalanceInfo2" table="BalanceInfo2">
		<cache usage="read-write"/> 
		<id name="id" column="id" length="32">
			<generator class="uuid.hex"/>
		</id>
		<property name="name"/>
		<property name="spec"/>
		<property name="unitName"/>
		<property name="f1"/>		
		<property name="f2"/>
		<property name="f1A"/>		
		<property name="f2A"/>
		<property name="f3A"/>
		
		<property name="f5"/>
		<property name="f5A"/>
		<property name="f5B"/>
		<property name="f6"/>
		<property name="f7"/>
		<property name="f8"/>
		<property name="f9"/>
		
		<property name="f11"/>
		<property name="f12"/>		
		<many-to-one lazy="false"      name="company" column="coid" class="com.bestway.bcus.system.entity.Company" index="BalanceInfo_company"/>
	</class>
</hibernate-mapping>
<!-- parsed in 0ms -->

		